{"name":"iprcibgs1744","license":"CC-BY-NC","indexed_at":"2017-09-28T14:14:47.824Z","period":[1395,1395],"category":["budget"],"maintainer":[{"lang":"en","text":"Small Media Foundation"},{"lang":"fa","text":"اسمال مدیا"}],"keywords":[{"lang":"en","wordlist":["budget","budget settlement"]},{"lang":"fa","wordlist":["بودجه","تفریغ بودجه"]}],"author":{"web":"http://rc.majlis.ir/fa/report/show/1021290","name":[{"lang":"fa","text":"مرکز پژوهش‌های مجلس شورای اسلامی"},{"lang":"en","text":"Islamic Parliament Research Center Of Iran"}]},"title":[{"lang":"en","text":"Budget settlement single article of budget law of the country in 1395"},{"lang":"fa","text":"تفريغ ماده واحده قانون بودجه سال ۱۳۹۵ كل کشور"}],"description":[{"lang":"fa","text":"این داده از سایت دیوان محاسبه کل کشور گرفته شده است."},{"lang":"en","text":"Dataset extracted from the website of Supreme Audit Court."}],"resources":[{"url":[{"lang":"fa","link":"http://iod.dataset.s3.amazonaws.com/bgs/iprcibgs1744fa.csv"},{"lang":"en","link":"http://iod.dataset.s3.amazonaws.com/bgs/iprcibgs1744en.csv"}],"title":[{"lang":"en","text":"Budget settlement single article of budget law of the country in 1395"},{"lang":"fa","text":"تفريغ ماده واحده قانون بودجه سال ۱۳۹۵ كل کشور"}],"sources":[{"name":"Islamic Parliament Research Center Of Iran","web":"http://rc.majlis.ir/fa/report/show/1021290"}],"schema":{"format":"csv","fields":[{"name":"title","type":"string"},{"name":"لایحه (میلیارد ریال - درصد)","type":"string"},{"name":"مصوب (میلیارد ریال – درصد)","type":"string"},{"name":"تغییرات مجلس (میلیارد ریال – درصد)","type":"string"},{"name":"عملکرد (میلیارد ریال – درصد)","type":"string"},{"name":"میزان انحراف عملکرد از لایحه (میلیارد ریال – درصد)","type":"string"},{"name":"میزان انحراف عملکرد از مصوب (میلیارد ریال – درصد)","type":"string"},{"name":"درصد تحقق نسبت به لایحه (میلیارد ریال – درصد)","type":"string"}]}}],"updated_at":"2017-09-28T14:14:47.824Z"}