{"name":"tpotd1738","license":"CC-BY-NC","indexed_at":"2017-04-19T15:08:45.079Z","period":[1392,1392],"category":["trade"],"maintainer":[{"lang":"en","text":"Small Media Foundation"},{"lang":"fa","text":"اسمال مدیا"}],"keywords":[{"lang":"en","wordlist":["business partners","10 nusiness partner","non-oil exports","Importation"]},{"lang":"fa","wordlist":["شرکای تجاری","۱۰ شریک تجاری","صادرات غیرنفتی","واردات"]}],"author":{"web":"http://www.tpo.ir/uploads/modiranarshad-12mah-92_3536.pdf","name":[{"lang":"fa","text":"سازمان توسعه تجارت ایران"},{"lang":"en","text":"Trade Promotion Organization of Iran"}]},"title":[{"lang":"en","text":"The most important target markets of goods in 1392"},{"lang":"fa","text":"مهمترين بازارهای هدف كالا در سال ۱۳۹۲"}],"description":[{"lang":"fa","text":"این داده از صفحه ۱۳، گزارش عملکرد تجارت خارجی کشور سال ۱۳۹۲، استخراج شده است."},{"lang":"en","text":"Dataset exctracted from page 13, Report of country's foreign trade performance in 1392."}],"resources":[{"url":[{"lang":"fa","link":"http://iod.dataset.s3.amazonaws.com/td/tpotd1738fa.csv"},{"lang":"en","link":"http://iod.dataset.s3.amazonaws.com/td/tpotd1738en.csv"}],"title":[{"lang":"en","text":"The most important target markets of goods in 1392"},{"lang":"fa","text":"مهمترين بازارهای هدف كالا در سال ۱۳۹۲"}],"sources":[{"name":"Trade Promotion Organization of Iran","web":"http://www.tpo.ir/uploads/modiranarshad-12mah-92_3536.pdf"}],"schema":{"format":"csv","fields":[{"name":"Rating in 1392","type":"string"},{"name":"Country Name","type":"string"},{"name":"The value of exports in 1392 - million dollars","type":"string"},{"name":"Percentage of value of total exports","type":"string"},{"name":"Value changes percentage comparing to 1391","type":"string"}]}}],"updated_at":"2017-04-19T15:08:45.079Z"}